[
  { "level": 1, "expRequired": 0, "atk": 0, "def": 0, "hp": 0, "mp": 0 },
  { "level": 2, "expRequired": 100, "atk": 0, "def": 0, "hp": 20, "mp": 20 },
  { "level": 3, "expRequired": 200, "atk": 0, "def": 0, "hp": 30, "mp": 30 },
  { "level": 4, "expRequired": 600, "atk": 1, "def": 0, "hp": 38, "mp": 38 },
  { "level": 5, "expRequired": 1000, "atk": 1, "def": 0, "hp": 44, "mp": 44 },
  { "level": 6, "expRequired": 1600, "atk": 1, "def": 0, "hp": 49, "mp": 49 },
  { "level": 7, "expRequired": 2400, "atk": 1, "def": 1, "hp": 53, "mp": 53 },
  { "level": 8, "expRequired": 3500, "atk": 1, "def": 1, "hp": 56, "mp": 56 },
  { "level": 9, "expRequired": 5000, "atk": 1, "def": 1, "hp": 59, "mp": 59 },
  { "level": 10, "expRequired": 7500, "atk": 1, "def": 1, "hp": 62, "mp": 62 },
  { "level": 11, "expRequired": 9500, "atk": 1, "def": 1, "hp": 64, "mp": 64 },
  { "level": 12, "expRequired": 12000, "atk": 2, "def": 1, "hp": 66, "mp": 66 },
  { "level": 13, "expRequired": 15000, "atk": 2, "def": 1, "hp": 68, "mp": 68 },
  { "level": 14, "expRequired": 18500, "atk": 2, "def": 1, "hp": 70, "mp": 70 },
  { "level": 15, "expRequired": 22500, "atk": 2, "def": 2, "hp": 72, "mp": 72 },
  { "level": 16, "expRequired": 27000, "atk": 2, "def": 2, "hp": 74, "mp": 74 },
  { "level": 17, "expRequired": 32000, "atk": 2, "def": 2, "hp": 76, "mp": 76 },
  { "level": 18, "expRequired": 38000, "atk": 2, "def": 2, "hp": 78, "mp": 78 },
  { "level": 19, "expRequired": 45000, "atk": 2, "def": 2, "hp": 80, "mp": 80 },
  { "level": 20, "expRequired": 55000, "atk": 3, "def": 2, "hp": 82, "mp": 82 },
  { "level": 21, "expRequired": 66000, "atk": 3, "def": 2, "hp": 83, "mp": 83 },
  { "level": 22, "expRequired": 78000, "atk": 3, "def": 2, "hp": 84, "mp": 84 },
  { "level": 23, "expRequired": 92000, "atk": 3, "def": 3, "hp": 85, "mp": 85 },
  { "level": 24, "expRequired": 108000, "atk": 3, "def": 3, "hp": 86, "mp": 86 },
  { "level": 25, "expRequired": 125000, "atk": 3, "def": 3, "hp": 87, "mp": 87 },
  { "level": 26, "expRequired": 145000, "atk": 3, "def": 3, "hp": 88, "mp": 88 },
  { "level": 27, "expRequired": 168000, "atk": 3, "def": 3, "hp": 89, "mp": 89 },
  { "level": 28, "expRequired": 195000, "atk": 4, "def": 3, "hp": 90, "mp": 90 },
  { "level": 29, "expRequired": 225000, "atk": 4, "def": 3, "hp": 91, "mp": 91 },
  { "level": 30, "expRequired": 260000, "atk": 4, "def": 3, "hp": 92, "mp": 92 },
  { "level": 31, "expRequired": 300000, "atk": 4, "def": 3, "hp": 93, "mp": 93 },
  { "level": 32, "expRequired": 345000, "atk": 4, "def": 4, "hp": 94, "mp": 94 },
  { "level": 33, "expRequired": 400000, "atk": 4, "def": 4, "hp": 95, "mp": 95 },
  { "level": 34, "expRequired": 460000, "atk": 4, "def": 4, "hp": 96, "mp": 96 },
  { "level": 35, "expRequired": 530000, "atk": 4, "def": 4, "hp": 97, "mp": 97 },
  { "level": 36, "expRequired": 610000, "atk": 5, "def": 4, "hp": 98, "mp": 98 },
  { "level": 37, "expRequired": 700000, "atk": 5, "def": 4, "hp": 99, "mp": 99 },
  { "level": 38, "expRequired": 810000, "atk": 5, "def": 4, "hp": 100, "mp": 100 },
  { "level": 39, "expRequired": 930000, "atk": 5, "def": 4, "hp": 101, "mp": 101 },
  { "level": 40, "expRequired": 1070000, "atk": 5, "def": 4, "hp": 102, "mp": 102 },
  { "level": 41, "expRequired": 1230000, "atk": 5, "def": 5, "hp": 103, "mp": 103 },
  { "level": 42, "expRequired": 1410000, "atk": 5, "def": 5, "hp": 104, "mp": 104 },
  { "level": 43, "expRequired": 1610000, "atk": 5, "def": 5, "hp": 105, "mp": 105 },
  { "level": 44, "expRequired": 1840000, "atk": 6, "def": 5, "hp": 106, "mp": 106 },
  { "level": 45, "expRequired": 2100000, "atk": 6, "def": 5, "hp": 107, "mp": 107 },
  { "level": 46, "expRequired": 2400000, "atk": 6, "def": 5, "hp": 108, "mp": 108 },
  { "level": 47, "expRequired": 2750000, "atk": 6, "def": 5, "hp": 109, "mp": 109 },
  { "level": 48, "expRequired": 3150000, "atk": 6, "def": 5, "hp": 110, "mp": 110 },
  { "level": 49, "expRequired": 3600000, "atk": 6, "def": 5, "hp": 111, "mp": 111 },
  { "level": 50, "expRequired": 4150000, "atk": 6, "def": 5, "hp": 112, "mp": 112 }
]