{
  "player": {
    "x": 0,
    "y": 0,
    "_maxHp": 50,
    "hp": 50,
    "_maxMp": 50,
    "mp": 50,
    "atk": 10,
    "def": 5,
    "agi": 5,
    "eva": 0,
    "crit": 0,
    "gold": 0,
    "exp": 0,
    "level": 1,
    "karma": 0,
    "inventoryMax": 15,
    "inventory": [
      {
        "id": "wood_stick_85c46acc187a4d83",
        "label": "\u001b[37m⚪ 나무 막대\u001b[0m",
        "type": "weapon",
        "atkRange": [
          1,
          3
        ],
        "critRange": [
          0,
          0
        ],
        "price": 0,
        "sellPrice": 0,
        "description": "길바닥을 굴러다니는 나무 막대",
        "quantity": 1,
        "maxRarity": "COMMON",
        "atk": 2,
        "crit": 0,
        "rarity": "COMMON",
        "x": 0,
        "y": 1
      },
      {
        "id": "rags_c062b48f5f05642f",
        "label": "\u001b[37m⚪ 장인의 누더기\u001b[0m",
        "type": "armor",
        "defRange": [
          1,
          2
        ],
        "evaRange": [
          0,
          0
        ],
        "price": 0,
        "sellPrice": 0,
        "description": "길바닥을 굴러다니는 망자의 천",
        "quantity": 1,
        "maxRarity": "COMMON",
        "def": 2,
        "eva": 0,
        "rarity": "COMMON",
        "x": 0,
        "y": 1
      },
      {
        "id": "nut",
        "label": "도토리",
        "type": "food",
        "hpHeal": 2,
        "price": 5,
        "sellPrice": 1,
        "description": "작고 영양가 있는 도토리로, 아주 소량의 체력을 회복합니다.",
        "quantity": 1,
        "x": 0,
        "y": 1
      }
    ],
    "_maxMemorize": 4,
    "memorize": [
      "RAISE_SKELETON",
      "FOCUS_FIRE"
    ],
    "equipped": {
      "weapon": null,
      "armor": null
    },
    "unlockedSkills": [
      "RAISE_SKELETON",
      "FOCUS_FIRE"
    ],
    "skeletonSubspace": [],
    "subspaceLimit": 1,
    "skeleton": [],
    "_maxSkeleton": 2,
    "upgradeLimit": 5,
    "golemUpgrade": [],
    "knightUpgrade": []
  },
  "sceneId": "B2_Transit_Area",
  "npcs": {
    "states": {
      "kane_leader": {
        "hp": 150,
        "isAlive": true,
        "reborn": false,
        "relation": 0
      },
      "maya_tech": {
        "hp": 30,
        "isAlive": true,
        "reborn": false,
        "relation": 0
      },
      "jax_seeker": {
        "hp": 50,
        "isAlive": true,
        "reborn": false,
        "relation": 0
      },
      "elevator": {
        "hp": 8000,
        "isAlive": true,
        "reborn": false,
        "relation": 0
      },
      "portal": {
        "hp": 8000,
        "isAlive": true,
        "reborn": false,
        "relation": 0
      },
      "death": {
        "hp": 3000,
        "isAlive": true,
        "reborn": false,
        "relation": 0
      },
      "first_boss": {
        "hp": 80,
        "isAlive": true,
        "reborn": false,
        "relation": 0
      },
      "second_boss": {
        "hp": 10,
        "isAlive": true,
        "reborn": false,
        "relation": 0
      },
      "third_boss": {
        "hp": 10,
        "isAlive": true,
        "reborn": false,
        "relation": 0
      },
      "dr_zed": {
        "hp": 1500,
        "isAlive": true,
        "reborn": false,
        "relation": 0
      },
      "echo": {
        "hp": 999,
        "isAlive": true,
        "reborn": false,
        "relation": 0
      },
      "ratty": {
        "hp": 30,
        "isAlive": true,
        "reborn": false,
        "relation": 0
      }
    },
    "factionHostility": {},
    "factionContribution": {}
  },
  "drop": null,
  "completedEvents": [
    "START_GAME",
    "item-tutorial",
    "first_talk_death"
  ]
}